CHANGELOG.md
LICENSE
MANIFEST.in
README.rst
setup.py
burrito/__init__.py
burrito/parameters.py
burrito/util.py
burrito.egg-info/PKG-INFO
burrito.egg-info/SOURCES.txt
burrito.egg-info/dependency_links.txt
burrito.egg-info/requires.txt
burrito.egg-info/top_level.txt
burrito/tests/__init__.py
burrito/tests/test_parameters.py
burrito/tests/test_util.py